pyu/__init__.py
pyu/cli.py
pyu/profiling/README.md
pyu/profiling/__init__.py
pyu/profiling/exceptions.py
pyu/profiling/memory.py
pyu/profiling/stats.py
pyu/profiling/time.py
pyu/profiling/writing.py
raven_pyu-1.0.2.dist-info/licenses/LICENSE
static/logo.png
tests/__init__.py
tests/utils.py
tests/profiling/test_memory.py
tests/profiling/test_time.py
raven_pyu-1.0.2.dist-info/METADATA
raven_pyu-1.0.2.dist-info/WHEEL
raven_pyu-1.0.2.dist-info/entry_points.txt
raven_pyu-1.0.2.dist-info/top_level.txt
raven_pyu-1.0.2.dist-info/RECORD
